authese/__init__.py
authese/authenticator.py
authese/environment.py
authese-0.0.2.dist-info/METADATA
authese-0.0.2.dist-info/WHEEL
authese-0.0.2.dist-info/top_level.txt
authese-0.0.2.dist-info/RECORD
