Metadata-Version: 2.1
Name: authese
Version: 0.0.2
Summary: OpenID Connect JWT Token Snatcher
Author-email: Joren Boulanger <joren@adhese.eu>, Pawel Szumanski <pawel.szumanski@adhese.eu>, Sven Schittecatte <sven.schittecatte@adhese.eu>
Project-URL: Homepage, https://github.com/adhese/spark/authese
Project-URL: Issues, https://github.com/adhese/spark/authese/issues
Classifier: Programming Language :: Python :: 3
Classifier: License :: OSI Approved :: MIT License
Classifier: Operating System :: OS Independent
Requires-Python: >=3.8
